django_dynamodb_cache/__init__.py
django_dynamodb_cache/backend.py
django_dynamodb_cache/cache.py
django_dynamodb_cache/dynamodb.py
django_dynamodb_cache/encode/__init__.py
django_dynamodb_cache/encode/base.py
django_dynamodb_cache/encode/pickle.py
django_dynamodb_cache/exceptions.py
django_dynamodb_cache/helper.py
django_dynamodb_cache/management/__init__.py
django_dynamodb_cache/management/commands/__init__.py
django_dynamodb_cache/management/commands/createcachetable.py
django_dynamodb_cache/settings.py
django_dynamodb_cache-0.6.0.dist-info/LICENSE
django_dynamodb_cache-0.6.0.dist-info/METADATA
django_dynamodb_cache-0.6.0.dist-info/WHEEL
django_dynamodb_cache-0.6.0.dist-info/RECORD
