Metadata-Version: 2.1
Name: django-dynamodb-cache
Version: 0.6.0
Summary: 
Home-page: https://github.com/xncbf/django-dynamodb-cache
License: MIT
Keywords: django,dynamodb,cache,django cache backend
Author: xncbf
Author-email: xncbf12@gmail.com
Requires-Python: >=3.8,<4.0
Classifier: Framework :: Django :: 3.2
Classifier: Framework :: Django :: 4.2
Classifier: Framework :: Django :: 5.0
Classifier: License :: OSI Approved :: MIT License
Classifier: Programming Language :: Python :: 3
Classifier: Programming Language :: Python :: 3.8
Classifier: Programming Language :: Python :: 3.9
Classifier: Programming Language :: Python :: 3.10
Classifier: Programming Language :: Python :: 3.11
Classifier: Programming Language :: Python :: 3.12
Requires-Dist: Django (>=3.2,<6)
Requires-Dist: boto3 (>=1.21.9,<2.0.0)
Requires-Dist: botocore (>=1.24.9,<2.0.0)
Project-URL: Repository, https://github.com/xncbf/django-dynamodb-cache
